
{
  "parent": "xercapaint:recipes/root",
  "rewards": {
    "recipes": [
      "xercapaint:item_canvas"
    ]
  },
  "criteria": {
    "has_item": {
      "trigger": "minecraft:inventory_changed",
      "conditions": {
        "items": [
          {"items": ["minecraft:paper"]}
        ]
      }
    },
    "has_the_recipe": {
      "trigger": "minecraft:recipe_unlocked",
      "conditions": {
        "recipe": "xercapaint:item_canvas"
      }
    }
  },
  "requirements": [
    [
      "has_item",
      "has_the_recipe"
    ]
  ]
}
        