{
  "minecraft:recipes/decorations/stone_brick_walls_from_stone_stonecutting": {
    "criteria": {
      "has_stone": "2019-10-27 22:57:37 +0300"
    },
    "done": true
  },
  "minecraft:recipes/building_blocks/stone_brick_stairs_from_stone_stonecutting": {
    "criteria": {
      "has_stone": "2019-10-27 22:57:37 +0300"
    },
    "done": true
  },
  "minecraft:recipes/decorations/slime_block": {
    "criteria": {
      "has_at_least_9_slime_ball": "2019-10-27 23:00:37 +0300"
    },
    "done": true
  },
  "xercamusic:achievements/root": {
    "criteria": {
      "crafting_table": "2019-10-27 22:57:37 +0300"
    },
    "done": true
  },
  "minecraft:recipes/building_blocks/smooth_stone": {
    "criteria": {
      "has_stone": "2019-10-27 22:57:37 +0300"
    },
    "done": true
  },
  "minecraft:recipes/misc/composter": {
    "criteria": {
      "has_wooden_fences": "2019-11-13 14:21:42 +0300"
    },
    "done": true
  },
  "minecraft:recipes/decorations/chest": {
    "criteria": {
      "has_lots_of_items": "2019-10-28 00:10:20 +0300"
    },
    "done": true
  },
  "minecraft:recipes/building_blocks/stone_slab_from_stone_stonecutting": {
    "criteria": {
      "has_stone": "2019-10-27 22:57:37 +0300"
    },
    "done": true
  },
  "minecraft:recipes/building_blocks/stone_stairs_from_stone_stonecutting": {
    "criteria": {
      "has_stone": "2019-10-27 22:57:37 +0300"
    },
    "done": true
  },
  "minecraft:recipes/building_blocks/chiseled_stone_bricks_stone_from_stonecutting": {
    "criteria": {
      "has_stone": "2019-10-27 22:57:37 +0300"
    },
    "done": true
  },
  "xercapaint:recipes/item_canvas_large": {
    "criteria": {
      "has_item": "2019-11-07 17:46:15 +0300"
    },
    "done": true
  },
  "minecraft:recipes/building_blocks/stone_bricks": {
    "criteria": {
      "has_stone": "2019-10-27 22:57:37 +0300"
    },
    "done": true
  },
  "minecraft:recipes/building_blocks/stone_bricks_from_stone_stonecutting": {
    "criteria": {
      "has_stone": "2019-10-27 22:57:37 +0300"
    },
    "done": true
  },
  "minecraft:story/root": {
    "criteria": {
      "crafting_table": "2019-11-07 17:46:36 +0300"
    },
    "done": true
  },
  "minecraft:recipes/redstone/stone_button": {
    "criteria": {
      "has_stone": "2019-10-27 22:57:37 +0300"
    },
    "done": true
  },
  "minecraft:recipes/misc/slime_ball": {
    "criteria": {
      "has_at_least_9_slime_ball": "2019-10-27 23:00:37 +0300"
    },
    "done": true
  },
  "minecraft:recipes/redstone/sticky_piston": {
    "criteria": {
      "has_slime_ball": "2019-10-27 23:00:28 +0300"
    },
    "done": true
  },
  "minecraft:recipes/building_blocks/stone_slab": {
    "criteria": {
      "has_stone": "2019-10-27 22:57:37 +0300"
    },
    "done": true
  },
  "minecraft:recipes/redstone/stone_pressure_plate": {
    "criteria": {
      "has_stone": "2019-10-27 22:57:37 +0300"
    },
    "done": true
  },
  "minecraft:recipes/tools/lead": {
    "criteria": {
      "has_slime_ball": "2019-10-27 23:00:28 +0300"
    },
    "done": true
  },
  "minecraft:recipes/building_blocks/stone_brick_slab_from_stone_stonecutting": {
    "criteria": {
      "has_stone": "2019-10-27 22:57:37 +0300"
    },
    "done": true
  },
  "minecraft:recipes/decorations/stonecutter": {
    "criteria": {
      "has_stone": "2019-10-27 22:57:37 +0300"
    },
    "done": true
  },
  "minecraft:recipes/building_blocks/stone_stairs": {
    "criteria": {
      "has_stone": "2019-10-27 22:57:37 +0300"
    },
    "done": true
  },
  "minecraft:adventure/adventuring_time": {
    "criteria": {
      "minecraft:plains": "2019-10-27 22:57:29 +0300"
    },
    "done": false
  },
  "DataVersion": 1976
}