
{
  "parent": "xercamod:recipes/root",
  "rewards": {
    "recipes": [
      "xercamod:item_melon_cupcake"
    ]
  },
  "criteria": {
    "has_item": {
      "trigger": "minecraft:inventory_changed",
      "conditions": {
        "items": [
          {"item": "minecraft:melon"}
        ]
      }
    },
    "has_the_recipe": {
      "trigger": "minecraft:recipe_unlocked",
      "conditions": {
        "recipe": "xercamod:item_melon_cupcake"
      }
    }
  },
  "requirements": [
    [
      "has_item",
      "has_the_recipe"
    ]
  ]
}
        